networking_spp/__init__.py
networking_spp/_i18n.py
networking_spp/agent/__init__.py
networking_spp/agent/config.py
networking_spp/agent/spp_agent.py
networking_spp/agent/spp_api.py
networking_spp/common/__init__.py
networking_spp/common/etcd_client.py
networking_spp/common/etcd_config.py
networking_spp/common/etcd_key.py
networking_spp/mech_driver/__init__.py
networking_spp/mech_driver/mech_spp.py
networking_spp/service_drivers/__init__.py
networking_spp/service_drivers/taas.py
networking_spp/tests/__init__.py
networking_spp/tests/dpdk-app/l2_ping_pong/Makefile
networking_spp/tests/dpdk-app/l2_ping_pong/l2_ping_pong.c
networking_spp/tests/tempest/__init__.py
networking_spp/tests/tempest/plugin.py
networking_spp/tests/tempest/scenario/__init__.py
networking_spp/tests/tempest/scenario/test_spp.py
networking_spp/tests/unit/__init__.py
networking_spp/tests/unit/test_mech_spp.py
networking_spp/tests/unit/test_service_taas.py
networking_spp/tests/unit/test_spp_agent.py
networking_spp/tests/unit/test_spp_api.py
networking_spp-21.0.0.dist-info/DESCRIPTION.rst
networking_spp-21.0.0.dist-info/METADATA
networking_spp-21.0.0.dist-info/RECORD
networking_spp-21.0.0.dist-info/WHEEL
networking_spp-21.0.0.dist-info/entry_points.txt
networking_spp-21.0.0.dist-info/metadata.json
networking_spp-21.0.0.dist-info/pbr.json
networking_spp-21.0.0.dist-info/top_level.txt
